{
    "Ciudades": {
        "105": {
            "Nombre ciudad": "Medellin",
            "Codigo Postal": 105,
            "Poblacion": 7777,
            "Pais": "Colombia"
        },
        "22": {
            "Nombre ciudad": "Bucaramanga",
            "Codigo Postal": 22,
            "Poblacion": 2222222,
            "Pais": "Colombia"
        },
        "999999": {
            "Nombre ciudad": "aa",
            "Codigo Postal": 999999,
            "Poblacion": 33333,
            "Pais": "aaaaaaaaa"
        },
        "39": {
            "Nombre ciudad": "Cartageeeeneeeeeeeena",
            "Codigo Postal": 39,
            "Poblacion": 100000,
            "Pais": "Colombia"
        },
        "34": {
            "Nombre ciudad": "Bogota",
            "Codigo Postal": 34,
            "Poblacion": 2000000,
            "Pais": "Colombia"
        }
    }
}